Workbook

Sheet Summary
A1: Summary: can players survive and afford expansions?
A3: Measure | B3: Low | C3: Mid | D3: High
A4: Week 1 income (€) | B4: =Low!G5 -> 106.029 | C4: =Mid!G5 -> 191.52 | D4: =High!G5 -> 300.3
A5: Week 1 rent (€) | B5: =Low!J5 -> 130 | C5: =Mid!J5 -> 130 | D5: =High!J5 -> 130
A6: Week 1 cash left after rent (€) | B6: =Low!K5 -> -23.971 | C6: =Mid!K5 -> 45.62 | D6: =High!K5 -> 131.3
A7: First failed week | B7: =IFERROR(MATCH("FAIL",Low!N5:N30,0),"none in 26 wks") -> 1 | C7: =IFERROR(MATCH("FAIL",Mid!N5:N30,0),"none in 26 wks") -> 11 | D7: =IFERROR(MATCH("FAIL",High!N5:N30,0),"none in 26 wks") -> 24
A8: Tier 2 active from week | B8: =IFERROR(MATCH(2,Low!B5:B30,0),"never") -> never | C8: =IFERROR(MATCH(2,Mid!B5:B30,0),"never") -> 7 | D8: =IFERROR(MATCH(2,High!B5:B30,0),"never") -> 4
A9: Tier 3 active from week | B9: =IFERROR(MATCH(3,Low!B5:B30,0),"never") -> never | C9: =IFERROR(MATCH(3,Mid!B5:B30,0),"never") -> never | D9: =IFERROR(MATCH(3,High!B5:B30,0),"never") -> 7
A10: Cash at end of week 26 (€) | B10: =Low!M30 -> -7486.3298 | C10: =Mid!M30 -> -4600.7 | D10: =High!M30 -> -884.36

Sheet Inputs
A1: Charity Shop Simulator: economy balance model
A2: Legend: blue text on yellow = editable input. Everything else is a formula. Change inputs and all sheets recalculate.
A4: Player skill scenario | B4: Low | C4: Mid | D4: High
A5: Average selling multiplier (0.5 to 2.5) | B5: 0.9 | C5: 1.2 | D5: 1.5
A6: Average patience multiplier (0.5 to 1.5) | B6: 0.9 | C6: 1 | D6: 1.1
A7: Share of items that get cleaned | B7: 0.2 | C7: 0.4 | D7: 0.6
A8: Share of customers who find an item in stock | B8: 0.85 | C8: 0.95 | D8: 1
A10: Scenario values are my assumptions about how well the player plays; replace them with real playtest averages.
A12: General inputs | B12: Value
A13: Days per week | B13: 7
A14: Starting cash (€) | B14: 0
A15: Rent in week 1 (€) | B15: 130 | C15: Tuned value (GDD currently says €150 and +€50)
A16: Rent increase per week (€) | B16: 30
A17: Extra customers per day for each week after week 1 | B17: 1
A18: Average baseline price of an item (€) | B18: =AVERAGE(5,1,7,3) -> 4 | C18: Mean of plates 5, books 1, t-shirts 7, balls 3 (assumes equal mix of items sold)
A19: Average cleaning score of a cleaned item (1.0 to 2.0) | B19: 1.5
A20: Cleaning supplies cost per use (€) | B20: =15/5 -> 3 | C20: €15 per 5 uses, from the GDD
A21: Free cleaning uses at start (week 1 only) | B21: 8 | C21: From the GDD
A22: Cash to keep in reserve after buying an expansion (€) | B22: 0
A23: Max customers per day the player can serve in the time limit | B23: 14 | C23: Assumption: about 3 minutes / 14 customers; this cap is what lets rent eventually beat income
A25: Shop tier | B25: Unlock week | C25: Cost (€) | D25: Extra rent per week (€) | E25: Base customers per day
A26: 1 | B26: 1 | C26: 0 | D26: 0 | E26: 5
A27: 2 | B27: 3 | C27: 150 | D27: 60 | E27: 8
A28: 3 | B28: 6 | C28: 300 | D28: 90 | E28: 11
A30: Expansion is bought at the end of a week once the unlock week is reached and cash covers the cost plus the reserve. The new tier applies from the next week.
A31: Model simplifications: every customer buys exactly one item; income is averaged per week; no rent cards, card penalties or damaged decorations; mess penalty ignored.

Sheet Low
A1: Low skill scenario: 26-week projection
A2: All cells are formulas driven by the Inputs sheet. Status FAIL means cash after paying rent is negative (run ends).
A4: Week | B4: Shop tier | C4: Customers per day | D4: Customers per week | E4: Average sale (€) | F4: Items sold | G4: Income (€) | H4: Cleaning uses | I4: Supplies cost (€) | J4: Rent due (€) | K4: Cash after rent (€) | L4: Expansion bought (€) | M4: Cash at week end (€) | N4: Status
A5: 1 | B5: 1 | C5: =MIN(INDEX(Inputs!$E$26:$E$28,B5)+(A5-1)*Inputs!$B$17,Inputs!$B$23) -> 5 | D5: =C5*Inputs!$B$13 -> 35 | E5: =Inputs!$B$18*(1+Inputs!B$7*(Inputs!$B$19-1))*Inputs!B$5*Inputs!B$6 -> 3.564 | F5: =D5*Inputs!B$8 -> 29.75 | G5: =F5*E5 -> 106.029 | H5: =F5*Inputs!B$7 -> 5.95 | I5: =MAX(0,H5-IF(A5=1,Inputs!$B$21,0))*Inputs!$B$20 -> 0 | J5: =Inputs!$B$15+(A5-1)*Inputs!$B$16+SUMIF(Inputs!$A$26:$A$28,"<="&B5,Inputs!$D$26:$D$28) -> 130 | K5: =Inputs!$B$14+G5-I5-J5 -> -23.971 | L5: =IF(B5>=COUNT(Inputs!$A$26:$A$28),0,IF(AND(K5>=0,A5>=INDEX(Inputs!$B$26:$B$28,B5+1),K5>=INDEX(Inputs!$C$26:$C$28,B5+1)+Inputs!$B$22),INDEX(Inputs!$C$26:$C$28,B5+1),0)) -> 0 | M5: =K5-L5 -> -23.971 | N5: =IF(K5<0,"FAIL","OK") -> FAIL
A6: 2 | B6: =B5+IF(L5>0,1,0) -> 1 | C6: =MIN(INDEX(Inputs!$E$26:$E$28,B6)+(A6-1)*Inputs!$B$17,Inputs!$B$23) -> 6 | D6: =C6*Inputs!$B$13 -> 42 | E6: =Inputs!$B$18*(1+Inputs!B$7*(Inputs!$B$19-1))*Inputs!B$5*Inputs!B$6 -> 3.564 | F6: =D6*Inputs!B$8 -> 35.7 | G6: =F6*E6 -> 127.2348 | H6: =F6*Inputs!B$7 -> 7.14 | I6: =MAX(0,H6-IF(A6=1,Inputs!$B$21,0))*Inputs!$B$20 -> 21.42 | J6: =Inputs!$B$15+(A6-1)*Inputs!$B$16+SUMIF(Inputs!$A$26:$A$28,"<="&B6,Inputs!$D$26:$D$28) -> 160 | K6: =M5+G6-I6-J6 -> -78.1562 | L6: =IF(B6>=COUNT(Inputs!$A$26:$A$28),0,IF(AND(K6>=0,A6>=INDEX(Inputs!$B$26:$B$28,B6+1),K6>=INDEX(Inputs!$C$26:$C$28,B6+1)+Inputs!$B$22),INDEX(Inputs!$C$26:$C$28,B6+1),0)) -> 0 | M6: =K6-L6 -> -78.1562 | N6: =IF(K6<0,"FAIL","OK") -> FAIL
A7: 3 | B7: =B6+IF(L6>0,1,0) -> 1 | C7: =MIN(INDEX(Inputs!$E$26:$E$28,B7)+(A7-1)*Inputs!$B$17,Inputs!$B$23) -> 7 | D7: =C7*Inputs!$B$13 -> 49 | E7: =Inputs!$B$18*(1+Inputs!B$7*(Inputs!$B$19-1))*Inputs!B$5*Inputs!B$6 -> 3.564 | F7: =D7*Inputs!B$8 -> 41.65 | G7: =F7*E7 -> 148.4406 | H7: =F7*Inputs!B$7 -> 8.33 | I7: =MAX(0,H7-IF(A7=1,Inputs!$B$21,0))*Inputs!$B$20 -> 24.99 | J7: =Inputs!$B$15+(A7-1)*Inputs!$B$16+SUMIF(Inputs!$A$26:$A$28,"<="&B7,Inputs!$D$26:$D$28) -> 190 | K7: =M6+G7-I7-J7 -> -144.7056 | L7: =IF(B7>=COUNT(Inputs!$A$26:$A$28),0,IF(AND(K7>=0,A7>=INDEX(Inputs!$B$26:$B$28,B7+1),K7>=INDEX(Inputs!$C$26:$C$28,B7+1)+Inputs!$B$22),INDEX(Inputs!$C$26:$C$28,B7+1),0)) -> 0 | M7: =K7-L7 -> -144.7056 | N7: =IF(K7<0,"FAIL","OK") -> FAIL
A8: 4 | B8: =B7+IF(L7>0,1,0) -> 1 | C8: =MIN(INDEX(Inputs!$E$26:$E$28,B8)+(A8-1)*Inputs!$B$17,Inputs!$B$23) -> 8 | D8: =C8*Inputs!$B$13 -> 56 | E8: =Inputs!$B$18*(1+Inputs!B$7*(Inputs!$B$19-1))*Inputs!B$5*Inputs!B$6 -> 3.564 | F8: =D8*Inputs!B$8 -> 47.6 | G8: =F8*E8 -> 169.6464 | H8: =F8*Inputs!B$7 -> 9.52 | I8: =MAX(0,H8-IF(A8=1,Inputs!$B$21,0))*Inputs!$B$20 -> 28.56 | J8: =Inputs!$B$15+(A8-1)*Inputs!$B$16+SUMIF(Inputs!$A$26:$A$28,"<="&B8,Inputs!$D$26:$D$28) -> 220 | K8: =M7+G8-I8-J8 -> -223.6192 | L8: =IF(B8>=COUNT(Inputs!$A$26:$A$28),0,IF(AND(K8>=0,A8>=INDEX(Inputs!$B$26:$B$28,B8+1),K8>=INDEX(Inputs!$C$26:$C$28,B8+1)+Inputs!$B$22),INDEX(Inputs!$C$26:$C$28,B8+1),0)) -> 0 | M8: =K8-L8 -> -223.6192 | N8: =IF(K8<0,"FAIL","OK") -> FAIL
A9: 5 | B9: =B8+IF(L8>0,1,0) -> 1 | C9: =MIN(INDEX(Inputs!$E$26:$E$28,B9)+(A9-1)*Inputs!$B$17,Inputs!$B$23) -> 9 | D9: =C9*Inputs!$B$13 -> 63 | E9: =Inputs!$B$18*(1+Inputs!B$7*(Inputs!$B$19-1))*Inputs!B$5*Inputs!B$6 -> 3.564 | F9: =D9*Inputs!B$8 -> 53.55 | G9: =F9*E9 -> 190.8522 | H9: =F9*Inputs!B$7 -> 10.71 | I9: =MAX(0,H9-IF(A9=1,Inputs!$B$21,0))*Inputs!$B$20 -> 32.13 | J9: =Inputs!$B$15+(A9-1)*Inputs!$B$16+SUMIF(Inputs!$A$26:$A$28,"<="&B9,Inputs!$D$26:$D$28) -> 250 | K9: =M8+G9-I9-J9 -> -314.897 | L9: =IF(B9>=COUNT(Inputs!$A$26:$A$28),0,IF(AND(K9>=0,A9>=INDEX(Inputs!$B$26:$B$28,B9+1),K9>=INDEX(Inputs!$C$26:$C$28,B9+1)+Inputs!$B$22),INDEX(Inputs!$C$26:$C$28,B9+1),0)) -> 0 | M9: =K9-L9 -> -314.897 | N9: =IF(K9<0,"FAIL","OK") -> FAIL
A10: 6 | B10: =B9+IF(L9>0,1,0) -> 1 | C10: =MIN(INDEX(Inputs!$E$26:$E$28,B10)+(A10-1)*Inputs!$B$17,Inputs!$B$23) -> 10 | D10: =C10*Inputs!$B$13 -> 70 | E10: =Inputs!$B$18*(1+Inputs!B$7*(Inputs!$B$19-1))*Inputs!B$5*Inputs!B$6 -> 3.564 | F10: =D10*Inputs!B$8 -> 59.5 | G10: =F10*E10 -> 212.058 | H10: =F10*Inputs!B$7 -> 11.9 | I10: =MAX(0,H10-IF(A10=1,Inputs!$B$21,0))*Inputs!$B$20 -> 35.7 | J10: =Inputs!$B$15+(A10-1)*Inputs!$B$16+SUMIF(Inputs!$A$26:$A$28,"<="&B10,Inputs!$D$26:$D$28) -> 280 | K10: =M9+G10-I10-J10 -> -418.539 | L10: =IF(B10>=COUNT(Inputs!$A$26:$A$28),0,IF(AND(K10>=0,A10>=INDEX(Inputs!$B$26:$B$28,B10+1),K10>=INDEX(Inputs!$C$26:$C$28,B10+1)+Inputs!$B$22),INDEX(Inputs!$C$26:$C$28,B10+1),0)) -> 0 | M10: =K10-L10 -> -418.539 | N10: =IF(K10<0,"FAIL","OK") -> FAIL
A11: 7 | B11: =B10+IF(L10>0,1,0) -> 1 | C11: =MIN(INDEX(Inputs!$E$26:$E$28,B11)+(A11-1)*Inputs!$B$17,Inputs!$B$23) -> 11 | D11: =C11*Inputs!$B$13 -> 77 | E11: =Inputs!$B$18*(1+Inputs!B$7*(Inputs!$B$19-1))*Inputs!B$5*Inputs!B$6 -> 3.564 | F11: =D11*Inputs!B$8 -> 65.45 | G11: =F11*E11 -> 233.2638 | H11: =F11*Inputs!B$7 -> 13.09 | I11: =MAX(0,H11-IF(A11=1,Inputs!$B$21,0))*Inputs!$B$20 -> 39.27 | J11: =Inputs!$B$15+(A11-1)*Inputs!$B$16+SUMIF(Inputs!$A$26:$A$28,"<="&B11,Inputs!$D$26:$D$28) -> 310 | K11: =M10+G11-I11-J11 -> -534.5452 | L11: =IF(B11>=COUNT(Inputs!$A$26:$A$28),0,IF(AND(K11>=0,A11>=INDEX(Inputs!$B$26:$B$28,B11+1),K11>=INDEX(Inputs!$C$26:$C$28,B11+1)+Inputs!$B$22),INDEX(Inputs!$C$26:$C$28,B11+1),0)) -> 0 | M11: =K11-L11 -> -534.5452 | N11: =IF(K11<0,"FAIL","OK") -> FAIL
A12: 8 | B12: =B11+IF(L11>0,1,0) -> 1 | C12: =MIN(INDEX(Inputs!$E$26:$E$28,B12)+(A12-1)*Inputs!$B$17,Inputs!$B$23) -> 12 | D12: =C12*Inputs!$B$13 -> 84 | E12: =Inputs!$B$18*(1+Inputs!B$7*(Inputs!$B$19-1))*Inputs!B$5*Inputs!B$6 -> 3.564 | F12: =D12*Inputs!B$8 -> 71.4 | G12: =F12*E12 -> 254.4696 | H12: =F12*Inputs!B$7 -> 14.28 | I12: =MAX(0,H12-IF(A12=1,Inputs!$B$21,0))*Inputs!$B$20 -> 42.84 | J12: =Inputs!$B$15+(A12-1)*Inputs!$B$16+SUMIF(Inputs!$A$26:$A$28,"<="&B12,Inputs!$D$26:$D$28) -> 340 | K12: =M11+G12-I12-J12 -> -662.9156 | L12: =IF(B12>=COUNT(Inputs!$A$26:$A$28),0,IF(AND(K12>=0,A12>=INDEX(Inputs!$B$26:$B$28,B12+1),K12>=INDEX(Inputs!$C$26:$C$28,B12+1)+Inputs!$B$22),INDEX(Inputs!$C$26:$C$28,B12+1),0)) -> 0 | M12: =K12-L12 -> -662.9156 | N12: =IF(K12<0,"FAIL","OK") -> FAIL
A13: 9 | B13: =B12+IF(L12>0,1,0) -> 1 | C13: =MIN(INDEX(Inputs!$E$26:$E$28,B13)+(A13-1)*Inputs!$B$17,Inputs!$B$23) -> 13 | D13: =C13*Inputs!$B$13 -> 91 | E13: =Inputs!$B$18*(1+Inputs!B$7*(Inputs!$B$19-1))*Inputs!B$5*Inputs!B$6 -> 3.564 | F13: =D13*Inputs!B$8 -> 77.35 | G13: =F13*E13 -> 275.6754 | H13: =F13*Inputs!B$7 -> 15.47 | I13: =MAX(0,H13-IF(A13=1,Inputs!$B$21,0))*Inputs!$B$20 -> 46.41 | J13: =Inputs!$B$15+(A13-1)*Inputs!$B$16+SUMIF(Inputs!$A$26:$A$28,"<="&B13,Inputs!$D$26:$D$28) -> 370 | K13: =M12+G13-I13-J13 -> -803.6502 | L13: =IF(B13>=COUNT(Inputs!$A$26:$A$28),0,IF(AND(K13>=0,A13>=INDEX(Inputs!$B$26:$B$28,B13+1),K13>=INDEX(Inputs!$C$26:$C$28,B13+1)+Inputs!$B$22),INDEX(Inputs!$C$26:$C$28,B13+1),0)) -> 0 | M13: =K13-L13 -> -803.6502 | N13: =IF(K13<0,"FAIL","OK") -> FAIL
A14: 10 | B14: =B13+IF(L13>0,1,0) -> 1 | C14: =MIN(INDEX(Inputs!$E$26:$E$28,B14)+(A14-1)*Inputs!$B$17,Inputs!$B$23) -> 14 | D14: =C14*Inputs!$B$13 -> 98 | E14: =Inputs!$B$18*(1+Inputs!B$7*(Inputs!$B$19-1))*Inputs!B$5*Inputs!B$6 -> 3.564 | F14: =D14*Inputs!B$8 -> 83.3 | G14: =F14*E14 -> 296.8812 | H14: =F14*Inputs!B$7 -> 16.66 | I14: =MAX(0,H14-IF(A14=1,Inputs!$B$21,0))*Inputs!$B$20 -> 49.98 | J14: =Inputs!$B$15+(A14-1)*Inputs!$B$16+SUMIF(Inputs!$A$26:$A$28,"<="&B14,Inputs!$D$26:$D$28) -> 400 | K14: =M13+G14-I14-J14 -> -956.749 | L14: =IF(B14>=COUNT(Inputs!$A$26:$A$28),0,IF(AND(K14>=0,A14>=INDEX(Inputs!$B$26:$B$28,B14+1),K14>=INDEX(Inputs!$C$26:$C$28,B14+1)+Inputs!$B$22),INDEX(Inputs!$C$26:$C$28,B14+1),0)) -> 0 | M14: =K14-L14 -> -956.749 | N14: =IF(K14<0,"FAIL","OK") -> FAIL
A15: 11 | B15: =B14+IF(L14>0,1,0) -> 1 | C15: =MIN(INDEX(Inputs!$E$26:$E$28,B15)+(A15-1)*Inputs!$B$17,Inputs!$B$23) -> 14 | D15: =C15*Inputs!$B$13 -> 98 | E15: =Inputs!$B$18*(1+Inputs!B$7*(Inputs!$B$19-1))*Inputs!B$5*Inputs!B$6 -> 3.564 | F15: =D15*Inputs!B$8 -> 83.3 | G15: =F15*E15 -> 296.8812 | H15: =F15*Inputs!B$7 -> 16.66 | I15: =MAX(0,H15-IF(A15=1,Inputs!$B$21,0))*Inputs!$B$20 -> 49.98 | J15: =Inputs!$B$15+(A15-1)*Inputs!$B$16+SUMIF(Inputs!$A$26:$A$28,"<="&B15,Inputs!$D$26:$D$28) -> 430 | K15: =M14+G15-I15-J15 -> -1139.8478 | L15: =IF(B15>=COUNT(Inputs!$A$26:$A$28),0,IF(AND(K15>=0,A15>=INDEX(Inputs!$B$26:$B$28,B15+1),K15>=INDEX(Inputs!$C$26:$C$28,B15+1)+Inputs!$B$22),INDEX(Inputs!$C$26:$C$28,B15+1),0)) -> 0 | M15: =K15-L15 -> -1139.8478 | N15: =IF(K15<0,"FAIL","OK") -> FAIL
A16: 12 | B16: =B15+IF(L15>0,1,0) -> 1 | C16: =MIN(INDEX(Inputs!$E$26:$E$28,B16)+(A16-1)*Inputs!$B$17,Inputs!$B$23) -> 14 | D16: =C16*Inputs!$B$13 -> 98 | E16: =Inputs!$B$18*(1+Inputs!B$7*(Inputs!$B$19-1))*Inputs!B$5*Inputs!B$6 -> 3.564 | F16: =D16*Inputs!B$8 -> 83.3 | G16: =F16*E16 -> 296.8812 | H16: =F16*Inputs!B$7 -> 16.66 | I16: =MAX(0,H16-IF(A16=1,Inputs!$B$21,0))*Inputs!$B$20 -> 49.98 | J16: =Inputs!$B$15+(A16-1)*Inputs!$B$16+SUMIF(Inputs!$A$26:$A$28,"<="&B16,Inputs!$D$26:$D$28) -> 460 | K16: =M15+G16-I16-J16 -> -1352.9466 | L16: =IF(B16>=COUNT(Inputs!$A$26:$A$28),0,IF(AND(K16>=0,A16>=INDEX(Inputs!$B$26:$B$28,B16+1),K16>=INDEX(Inputs!$C$26:$C$28,B16+1)+Inputs!$B$22),INDEX(Inputs!$C$26:$C$28,B16+1),0)) -> 0 | M16: =K16-L16 -> -1352.9466 | N16: =IF(K16<0,"FAIL","OK") -> FAIL
A17: 13 | B17: =B16+IF(L16>0,1,0) -> 1 | C17: =MIN(INDEX(Inputs!$E$26:$E$28,B17)+(A17-1)*Inputs!$B$17,Inputs!$B$23) -> 14 | D17: =C17*Inputs!$B$13 -> 98 | E17: =Inputs!$B$18*(1+Inputs!B$7*(Inputs!$B$19-1))*Inputs!B$5*Inputs!B$6 -> 3.564 | F17: =D17*Inputs!B$8 -> 83.3 | G17: =F17*E17 -> 296.8812 | H17: =F17*Inputs!B$7 -> 16.66 | I17: =MAX(0,H17-IF(A17=1,Inputs!$B$21,0))*Inputs!$B$20 -> 49.98 | J17: =Inputs!$B$15+(A17-1)*Inputs!$B$16+SUMIF(Inputs!$A$26:$A$28,"<="&B17,Inputs!$D$26:$D$28) -> 490 | K17: =M16+G17-I17-J17 -> -1596.0454 | L17: =IF(B17>=COUNT(Inputs!$A$26:$A$28),0,IF(AND(K17>=0,A17>=INDEX(Inputs!$B$26:$B$28,B17+1),K17>=INDEX(Inputs!$C$26:$C$28,B17+1)+Inputs!$B$22),INDEX(Inputs!$C$26:$C$28,B17+1),0)) -> 0 | M17: =K17-L17 -> -1596.0454 | N17: =IF(K17<0,"FAIL","OK") -> FAIL
... A30: 26 | B30: =B29+IF(L29>0,1,0) -> 1 | C30: =MIN(INDEX(Inputs!$E$26:$E$28,B30)+(A30-1)*Inputs!$B$17,Inputs!$B$23) -> 14 | D30: =C30*Inputs!$B$13 -> 98 | E30: =Inputs!$B$18*(1+Inputs!B$7*(Inputs!$B$19-1))*Inputs!B$5*Inputs!B$6 -> 3.564 | F30: =D30*Inputs!B$8 -> 83.3 | G30: =F30*E30 -> 296.8812 | H30: =F30*Inputs!B$7 -> 16.66 | I30: =MAX(0,H30-IF(A30=1,Inputs!$B$21,0))*Inputs!$B$20 -> 49.98 | J30: =Inputs!$B$15+(A30-1)*Inputs!$B$16+SUMIF(Inputs!$A$26:$A$28,"<="&B30,Inputs!$D$26:$D$28) -> 880 | K30: =M29+G30-I30-J30 -> -7486.3298 | L30: =IF(B30>=COUNT(Inputs!$A$26:$A$28),0,IF(AND(K30>=0,A30>=INDEX(Inputs!$B$26:$B$28,B30+1),K30>=INDEX(Inputs!$C$26:$C$28,B30+1)+Inputs!$B$22),INDEX(Inputs!$C$26:$C$28,B30+1),0)) -> 0 | M30: =K30-L30 -> -7486.3298 | N30: =IF(K30<0,"FAIL","OK") -> FAIL

Sheet Mid
A1: Mid skill scenario: 26-week projection
A2: All cells are formulas driven by the Inputs sheet. Status FAIL means cash after paying rent is negative (run ends).
A4: Week | B4: Shop tier | C4: Customers per day | D4: Customers per week | E4: Average sale (€) | F4: Items sold | G4: Income (€) | H4: Cleaning uses | I4: Supplies cost (€) | J4: Rent due (€) | K4: Cash after rent (€) | L4: Expansion bought (€) | M4: Cash at week end (€) | N4: Status
A5: 1 | B5: 1 | C5: =MIN(INDEX(Inputs!$E$26:$E$28,B5)+(A5-1)*Inputs!$B$17,Inputs!$B$23) -> 5 | D5: =C5*Inputs!$B$13 -> 35 | E5: =Inputs!$B$18*(1+Inputs!C$7*(Inputs!$B$19-1))*Inputs!C$5*Inputs!C$6 -> 5.76 | F5: =D5*Inputs!C$8 -> 33.25 | G5: =F5*E5 -> 191.52 | H5: =F5*Inputs!C$7 -> 13.3 | I5: =MAX(0,H5-IF(A5=1,Inputs!$B$21,0))*Inputs!$B$20 -> 15.9 | J5: =Inputs!$B$15+(A5-1)*Inputs!$B$16+SUMIF(Inputs!$A$26:$A$28,"<="&B5,Inputs!$D$26:$D$28) -> 130 | K5: =Inputs!$B$14+G5-I5-J5 -> 45.62 | L5: =IF(B5>=COUNT(Inputs!$A$26:$A$28),0,IF(AND(K5>=0,A5>=INDEX(Inputs!$B$26:$B$28,B5+1),K5>=INDEX(Inputs!$C$26:$C$28,B5+1)+Inputs!$B$22),INDEX(Inputs!$C$26:$C$28,B5+1),0)) -> 0 | M5: =K5-L5 -> 45.62 | N5: =IF(K5<0,"FAIL","OK") -> OK
A6: 2 | B6: =B5+IF(L5>0,1,0) -> 1 | C6: =MIN(INDEX(Inputs!$E$26:$E$28,B6)+(A6-1)*Inputs!$B$17,Inputs!$B$23) -> 6 | D6: =C6*Inputs!$B$13 -> 42 | E6: =Inputs!$B$18*(1+Inputs!C$7*(Inputs!$B$19-1))*Inputs!C$5*Inputs!C$6 -> 5.76 | F6: =D6*Inputs!C$8 -> 39.9 | G6: =F6*E6 -> 229.824 | H6: =F6*Inputs!C$7 -> 15.96 | I6: =MAX(0,H6-IF(A6=1,Inputs!$B$21,0))*Inputs!$B$20 -> 47.88 | J6: =Inputs!$B$15+(A6-1)*Inputs!$B$16+SUMIF(Inputs!$A$26:$A$28,"<="&B6,Inputs!$D$26:$D$28) -> 160 | K6: =M5+G6-I6-J6 -> 67.564 | L6: =IF(B6>=COUNT(Inputs!$A$26:$A$28),0,IF(AND(K6>=0,A6>=INDEX(Inputs!$B$26:$B$28,B6+1),K6>=INDEX(Inputs!$C$26:$C$28,B6+1)+Inputs!$B$22),INDEX(Inputs!$C$26:$C$28,B6+1),0)) -> 0 | M6: =K6-L6 -> 67.564 | N6: =IF(K6<0,"FAIL","OK") -> OK
A7: 3 | B7: =B6+IF(L6>0,1,0) -> 1 | C7: =MIN(INDEX(Inputs!$E$26:$E$28,B7)+(A7-1)*Inputs!$B$17,Inputs!$B$23) -> 7 | D7: =C7*Inputs!$B$13 -> 49 | E7: =Inputs!$B$18*(1+Inputs!C$7*(Inputs!$B$19-1))*Inputs!C$5*Inputs!C$6 -> 5.76 | F7: =D7*Inputs!C$8 -> 46.55 | G7: =F7*E7 -> 268.128 | H7: =F7*Inputs!C$7 -> 18.62 | I7: =MAX(0,H7-IF(A7=1,Inputs!$B$21,0))*Inputs!$B$20 -> 55.86 | J7: =Inputs!$B$15+(A7-1)*Inputs!$B$16+SUMIF(Inputs!$A$26:$A$28,"<="&B7,Inputs!$D$26:$D$28) -> 190 | K7: =M6+G7-I7-J7 -> 89.832 | L7: =IF(B7>=COUNT(Inputs!$A$26:$A$28),0,IF(AND(K7>=0,A7>=INDEX(Inputs!$B$26:$B$28,B7+1),K7>=INDEX(Inputs!$C$26:$C$28,B7+1)+Inputs!$B$22),INDEX(Inputs!$C$26:$C$28,B7+1),0)) -> 0 | M7: =K7-L7 -> 89.832 | N7: =IF(K7<0,"FAIL","OK") -> OK
A8: 4 | B8: =B7+IF(L7>0,1,0) -> 1 | C8: =MIN(INDEX(Inputs!$E$26:$E$28,B8)+(A8-1)*Inputs!$B$17,Inputs!$B$23) -> 8 | D8: =C8*Inputs!$B$13 -> 56 | E8: =Inputs!$B$18*(1+Inputs!C$7*(Inputs!$B$19-1))*Inputs!C$5*Inputs!C$6 -> 5.76 | F8: =D8*Inputs!C$8 -> 53.2 | G8: =F8*E8 -> 306.432 | H8: =F8*Inputs!C$7 -> 21.28 | I8: =MAX(0,H8-IF(A8=1,Inputs!$B$21,0))*Inputs!$B$20 -> 63.84 | J8: =Inputs!$B$15+(A8-1)*Inputs!$B$16+SUMIF(Inputs!$A$26:$A$28,"<="&B8,Inputs!$D$26:$D$28) -> 220 | K8: =M7+G8-I8-J8 -> 112.424 | L8: =IF(B8>=COUNT(Inputs!$A$26:$A$28),0,IF(AND(K8>=0,A8>=INDEX(Inputs!$B$26:$B$28,B8+1),K8>=INDEX(Inputs!$C$26:$C$28,B8+1)+Inputs!$B$22),INDEX(Inputs!$C$26:$C$28,B8+1),0)) -> 0 | M8: =K8-L8 -> 112.424 | N8: =IF(K8<0,"FAIL","OK") -> OK
A9: 5 | B9: =B8+IF(L8>0,1,0) -> 1 | C9: =MIN(INDEX(Inputs!$E$26:$E$28,B9)+(A9-1)*Inputs!$B$17,Inputs!$B$23) -> 9 | D9: =C9*Inputs!$B$13 -> 63 | E9: =Inputs!$B$18*(1+Inputs!C$7*(Inputs!$B$19-1))*Inputs!C$5*Inputs!C$6 -> 5.76 | F9: =D9*Inputs!C$8 -> 59.85 | G9: =F9*E9 -> 344.736 | H9: =F9*Inputs!C$7 -> 23.94 | I9: =MAX(0,H9-IF(A9=1,Inputs!$B$21,0))*Inputs!$B$20 -> 71.82 | J9: =Inputs!$B$15+(A9-1)*Inputs!$B$16+SUMIF(Inputs!$A$26:$A$28,"<="&B9,Inputs!$D$26:$D$28) -> 250 | K9: =M8+G9-I9-J9 -> 135.34 | L9: =IF(B9>=COUNT(Inputs!$A$26:$A$28),0,IF(AND(K9>=0,A9>=INDEX(Inputs!$B$26:$B$28,B9+1),K9>=INDEX(Inputs!$C$26:$C$28,B9+1)+Inputs!$B$22),INDEX(Inputs!$C$26:$C$28,B9+1),0)) -> 0 | M9: =K9-L9 -> 135.34 | N9: =IF(K9<0,"FAIL","OK") -> OK
A10: 6 | B10: =B9+IF(L9>0,1,0) -> 1 | C10: =MIN(INDEX(Inputs!$E$26:$E$28,B10)+(A10-1)*Inputs!$B$17,Inputs!$B$23) -> 10 | D10: =C10*Inputs!$B$13 -> 70 | E10: =Inputs!$B$18*(1+Inputs!C$7*(Inputs!$B$19-1))*Inputs!C$5*Inputs!C$6 -> 5.76 | F10: =D10*Inputs!C$8 -> 66.5 | G10: =F10*E10 -> 383.04 | H10: =F10*Inputs!C$7 -> 26.6 | I10: =MAX(0,H10-IF(A10=1,Inputs!$B$21,0))*Inputs!$B$20 -> 79.8 | J10: =Inputs!$B$15+(A10-1)*Inputs!$B$16+SUMIF(Inputs!$A$26:$A$28,"<="&B10,Inputs!$D$26:$D$28) -> 280 | K10: =M9+G10-I10-J10 -> 158.58 | L10: =IF(B10>=COUNT(Inputs!$A$26:$A$28),0,IF(AND(K10>=0,A10>=INDEX(Inputs!$B$26:$B$28,B10+1),K10>=INDEX(Inputs!$C$26:$C$28,B10+1)+Inputs!$B$22),INDEX(Inputs!$C$26:$C$28,B10+1),0)) -> 150 | M10: =K10-L10 -> 8.58 | N10: =IF(K10<0,"FAIL","OK") -> OK
A11: 7 | B11: =B10+IF(L10>0,1,0) -> 2 | C11: =MIN(INDEX(Inputs!$E$26:$E$28,B11)+(A11-1)*Inputs!$B$17,Inputs!$B$23) -> 14 | D11: =C11*Inputs!$B$13 -> 98 | E11: =Inputs!$B$18*(1+Inputs!C$7*(Inputs!$B$19-1))*Inputs!C$5*Inputs!C$6 -> 5.76 | F11: =D11*Inputs!C$8 -> 93.1 | G11: =F11*E11 -> 536.256 | H11: =F11*Inputs!C$7 -> 37.24 | I11: =MAX(0,H11-IF(A11=1,Inputs!$B$21,0))*Inputs!$B$20 -> 111.72 | J11: =Inputs!$B$15+(A11-1)*Inputs!$B$16+SUMIF(Inputs!$A$26:$A$28,"<="&B11,Inputs!$D$26:$D$28) -> 370 | K11: =M10+G11-I11-J11 -> 63.116 | L11: =IF(B11>=COUNT(Inputs!$A$26:$A$28),0,IF(AND(K11>=0,A11>=INDEX(Inputs!$B$26:$B$28,B11+1),K11>=INDEX(Inputs!$C$26:$C$28,B11+1)+Inputs!$B$22),INDEX(Inputs!$C$26:$C$28,B11+1),0)) -> 0 | M11: =K11-L11 -> 63.116 | N11: =IF(K11<0,"FAIL","OK") -> OK
A12: 8 | B12: =B11+IF(L11>0,1,0) -> 2 | C12: =MIN(INDEX(Inputs!$E$26:$E$28,B12)+(A12-1)*Inputs!$B$17,Inputs!$B$23) -> 14 | D12: =C12*Inputs!$B$13 -> 98 | E12: =Inputs!$B$18*(1+Inputs!C$7*(Inputs!$B$19-1))*Inputs!C$5*Inputs!C$6 -> 5.76 | F12: =D12*Inputs!C$8 -> 93.1 | G12: =F12*E12 -> 536.256 | H12: =F12*Inputs!C$7 -> 37.24 | I12: =MAX(0,H12-IF(A12=1,Inputs!$B$21,0))*Inputs!$B$20 -> 111.72 | J12: =Inputs!$B$15+(A12-1)*Inputs!$B$16+SUMIF(Inputs!$A$26:$A$28,"<="&B12,Inputs!$D$26:$D$28) -> 400 | K12: =M11+G12-I12-J12 -> 87.652 | L12: =IF(B12>=COUNT(Inputs!$A$26:$A$28),0,IF(AND(K12>=0,A12>=INDEX(Inputs!$B$26:$B$28,B12+1),K12>=INDEX(Inputs!$C$26:$C$28,B12+1)+Inputs!$B$22),INDEX(Inputs!$C$26:$C$28,B12+1),0)) -> 0 | M12: =K12-L12 -> 87.652 | N12: =IF(K12<0,"FAIL","OK") -> OK
A13: 9 | B13: =B12+IF(L12>0,1,0) -> 2 | C13: =MIN(INDEX(Inputs!$E$26:$E$28,B13)+(A13-1)*Inputs!$B$17,Inputs!$B$23) -> 14 | D13: =C13*Inputs!$B$13 -> 98 | E13: =Inputs!$B$18*(1+Inputs!C$7*(Inputs!$B$19-1))*Inputs!C$5*Inputs!C$6 -> 5.76 | F13: =D13*Inputs!C$8 -> 93.1 | G13: =F13*E13 -> 536.256 | H13: =F13*Inputs!C$7 -> 37.24 | I13: =MAX(0,H13-IF(A13=1,Inputs!$B$21,0))*Inputs!$B$20 -> 111.72 | J13: =Inputs!$B$15+(A13-1)*Inputs!$B$16+SUMIF(Inputs!$A$26:$A$28,"<="&B13,Inputs!$D$26:$D$28) -> 430 | K13: =M12+G13-I13-J13 -> 82.188 | L13: =IF(B13>=COUNT(Inputs!$A$26:$A$28),0,IF(AND(K13>=0,A13>=INDEX(Inputs!$B$26:$B$28,B13+1),K13>=INDEX(Inputs!$C$26:$C$28,B13+1)+Inputs!$B$22),INDEX(Inputs!$C$26:$C$28,B13+1),0)) -> 0 | M13: =K13-L13 -> 82.188 | N13: =IF(K13<0,"FAIL","OK") -> OK
A14: 10 | B14: =B13+IF(L13>0,1,0) -> 2 | C14: =MIN(INDEX(Inputs!$E$26:$E$28,B14)+(A14-1)*Inputs!$B$17,Inputs!$B$23) -> 14 | D14: =C14*Inputs!$B$13 -> 98 | E14: =Inputs!$B$18*(1+Inputs!C$7*(Inputs!$B$19-1))*Inputs!C$5*Inputs!C$6 -> 5.76 | F14: =D14*Inputs!C$8 -> 93.1 | G14: =F14*E14 -> 536.256 | H14: =F14*Inputs!C$7 -> 37.24 | I14: =MAX(0,H14-IF(A14=1,Inputs!$B$21,0))*Inputs!$B$20 -> 111.72 | J14: =Inputs!$B$15+(A14-1)*Inputs!$B$16+SUMIF(Inputs!$A$26:$A$28,"<="&B14,Inputs!$D$26:$D$28) -> 460 | K14: =M13+G14-I14-J14 -> 46.724 | L14: =IF(B14>=COUNT(Inputs!$A$26:$A$28),0,IF(AND(K14>=0,A14>=INDEX(Inputs!$B$26:$B$28,B14+1),K14>=INDEX(Inputs!$C$26:$C$28,B14+1)+Inputs!$B$22),INDEX(Inputs!$C$26:$C$28,B14+1),0)) -> 0 | M14: =K14-L14 -> 46.724 | N14: =IF(K14<0,"FAIL","OK") -> OK
A15: 11 | B15: =B14+IF(L14>0,1,0) -> 2 | C15: =MIN(INDEX(Inputs!$E$26:$E$28,B15)+(A15-1)*Inputs!$B$17,Inputs!$B$23) -> 14 | D15: =C15*Inputs!$B$13 -> 98 | E15: =Inputs!$B$18*(1+Inputs!C$7*(Inputs!$B$19-1))*Inputs!C$5*Inputs!C$6 -> 5.76 | F15: =D15*Inputs!C$8 -> 93.1 | G15: =F15*E15 -> 536.256 | H15: =F15*Inputs!C$7 -> 37.24 | I15: =MAX(0,H15-IF(A15=1,Inputs!$B$21,0))*Inputs!$B$20 -> 111.72 | J15: =Inputs!$B$15+(A15-1)*Inputs!$B$16+SUMIF(Inputs!$A$26:$A$28,"<="&B15,Inputs!$D$26:$D$28) -> 490 | K15: =M14+G15-I15-J15 -> -18.74 | L15: =IF(B15>=COUNT(Inputs!$A$26:$A$28),0,IF(AND(K15>=0,A15>=INDEX(Inputs!$B$26:$B$28,B15+1),K15>=INDEX(Inputs!$C$26:$C$28,B15+1)+Inputs!$B$22),INDEX(Inputs!$C$26:$C$28,B15+1),0)) -> 0 | M15: =K15-L15 -> -18.74 | N15: =IF(K15<0,"FAIL","OK") -> FAIL
A16: 12 | B16: =B15+IF(L15>0,1,0) -> 2 | C16: =MIN(INDEX(Inputs!$E$26:$E$28,B16)+(A16-1)*Inputs!$B$17,Inputs!$B$23) -> 14 | D16: =C16*Inputs!$B$13 -> 98 | E16: =Inputs!$B$18*(1+Inputs!C$7*(Inputs!$B$19-1))*Inputs!C$5*Inputs!C$6 -> 5.76 | F16: =D16*Inputs!C$8 -> 93.1 | G16: =F16*E16 -> 536.256 | H16: =F16*Inputs!C$7 -> 37.24 | I16: =MAX(0,H16-IF(A16=1,Inputs!$B$21,0))*Inputs!$B$20 -> 111.72 | J16: =Inputs!$B$15+(A16-1)*Inputs!$B$16+SUMIF(Inputs!$A$26:$A$28,"<="&B16,Inputs!$D$26:$D$28) -> 520 | K16: =M15+G16-I16-J16 -> -114.204 | L16: =IF(B16>=COUNT(Inputs!$A$26:$A$28),0,IF(AND(K16>=0,A16>=INDEX(Inputs!$B$26:$B$28,B16+1),K16>=INDEX(Inputs!$C$26:$C$28,B16+1)+Inputs!$B$22),INDEX(Inputs!$C$26:$C$28,B16+1),0)) -> 0 | M16: =K16-L16 -> -114.204 | N16: =IF(K16<0,"FAIL","OK") -> FAIL
A17: 13 | B17: =B16+IF(L16>0,1,0) -> 2 | C17: =MIN(INDEX(Inputs!$E$26:$E$28,B17)+(A17-1)*Inputs!$B$17,Inputs!$B$23) -> 14 | D17: =C17*Inputs!$B$13 -> 98 | E17: =Inputs!$B$18*(1+Inputs!C$7*(Inputs!$B$19-1))*Inputs!C$5*Inputs!C$6 -> 5.76 | F17: =D17*Inputs!C$8 -> 93.1 | G17: =F17*E17 -> 536.256 | H17: =F17*Inputs!C$7 -> 37.24 | I17: =MAX(0,H17-IF(A17=1,Inputs!$B$21,0))*Inputs!$B$20 -> 111.72 | J17: =Inputs!$B$15+(A17-1)*Inputs!$B$16+SUMIF(Inputs!$A$26:$A$28,"<="&B17,Inputs!$D$26:$D$28) -> 550 | K17: =M16+G17-I17-J17 -> -239.668 | L17: =IF(B17>=COUNT(Inputs!$A$26:$A$28),0,IF(AND(K17>=0,A17>=INDEX(Inputs!$B$26:$B$28,B17+1),K17>=INDEX(Inputs!$C$26:$C$28,B17+1)+Inputs!$B$22),INDEX(Inputs!$C$26:$C$28,B17+1),0)) -> 0 | M17: =K17-L17 -> -239.668 | N17: =IF(K17<0,"FAIL","OK") -> FAIL
... A30: 26 | B30: =B29+IF(L29>0,1,0) -> 2 | C30: =MIN(INDEX(Inputs!$E$26:$E$28,B30)+(A30-1)*Inputs!$B$17,Inputs!$B$23) -> 14 | D30: =C30*Inputs!$B$13 -> 98 | E30: =Inputs!$B$18*(1+Inputs!C$7*(Inputs!$B$19-1))*Inputs!C$5*Inputs!C$6 -> 5.76 | F30: =D30*Inputs!C$8 -> 93.1 | G30: =F30*E30 -> 536.256 | H30: =F30*Inputs!C$7 -> 37.24 | I30: =MAX(0,H30-IF(A30=1,Inputs!$B$21,0))*Inputs!$B$20 -> 111.72 | J30: =Inputs!$B$15+(A30-1)*Inputs!$B$16+SUMIF(Inputs!$A$26:$A$28,"<="&B30,Inputs!$D$26:$D$28) -> 940 | K30: =M29+G30-I30-J30 -> -4600.7 | L30: =IF(B30>=COUNT(Inputs!$A$26:$A$28),0,IF(AND(K30>=0,A30>=INDEX(Inputs!$B$26:$B$28,B30+1),K30>=INDEX(Inputs!$C$26:$C$28,B30+1)+Inputs!$B$22),INDEX(Inputs!$C$26:$C$28,B30+1),0)) -> 0 | M30: =K30-L30 -> -4600.7 | N30: =IF(K30<0,"FAIL","OK") -> FAIL

Sheet High
A1: High skill scenario: 26-week projection
A2: All cells are formulas driven by the Inputs sheet. Status FAIL means cash after paying rent is negative (run ends).
A4: Week | B4: Shop tier | C4: Customers per day | D4: Customers per week | E4: Average sale (€) | F4: Items sold | G4: Income (€) | H4: Cleaning uses | I4: Supplies cost (€) | J4: Rent due (€) | K4: Cash after rent (€) | L4: Expansion bought (€) | M4: Cash at week end (€) | N4: Status
A5: 1 | B5: 1 | C5: =MIN(INDEX(Inputs!$E$26:$E$28,B5)+(A5-1)*Inputs!$B$17,Inputs!$B$23) -> 5 | D5: =C5*Inputs!$B$13 -> 35 | E5: =Inputs!$B$18*(1+Inputs!D$7*(Inputs!$B$19-1))*Inputs!D$5*Inputs!D$6 -> 8.58 | F5: =D5*Inputs!D$8 -> 35 | G5: =F5*E5 -> 300.3 | H5: =F5*Inputs!D$7 -> 21 | I5: =MAX(0,H5-IF(A5=1,Inputs!$B$21,0))*Inputs!$B$20 -> 39 | J5: =Inputs!$B$15+(A5-1)*Inputs!$B$16+SUMIF(Inputs!$A$26:$A$28,"<="&B5,Inputs!$D$26:$D$28) -> 130 | K5: =Inputs!$B$14+G5-I5-J5 -> 131.3 | L5: =IF(B5>=COUNT(Inputs!$A$26:$A$28),0,IF(AND(K5>=0,A5>=INDEX(Inputs!$B$26:$B$28,B5+1),K5>=INDEX(Inputs!$C$26:$C$28,B5+1)+Inputs!$B$22),INDEX(Inputs!$C$26:$C$28,B5+1),0)) -> 0 | M5: =K5-L5 -> 131.3 | N5: =IF(K5<0,"FAIL","OK") -> OK
A6: 2 | B6: =B5+IF(L5>0,1,0) -> 1 | C6: =MIN(INDEX(Inputs!$E$26:$E$28,B6)+(A6-1)*Inputs!$B$17,Inputs!$B$23) -> 6 | D6: =C6*Inputs!$B$13 -> 42 | E6: =Inputs!$B$18*(1+Inputs!D$7*(Inputs!$B$19-1))*Inputs!D$5*Inputs!D$6 -> 8.58 | F6: =D6*Inputs!D$8 -> 42 | G6: =F6*E6 -> 360.36 | H6: =F6*Inputs!D$7 -> 25.2 | I6: =MAX(0,H6-IF(A6=1,Inputs!$B$21,0))*Inputs!$B$20 -> 75.6 | J6: =Inputs!$B$15+(A6-1)*Inputs!$B$16+SUMIF(Inputs!$A$26:$A$28,"<="&B6,Inputs!$D$26:$D$28) -> 160 | K6: =M5+G6-I6-J6 -> 256.06 | L6: =IF(B6>=COUNT(Inputs!$A$26:$A$28),0,IF(AND(K6>=0,A6>=INDEX(Inputs!$B$26:$B$28,B6+1),K6>=INDEX(Inputs!$C$26:$C$28,B6+1)+Inputs!$B$22),INDEX(Inputs!$C$26:$C$28,B6+1),0)) -> 0 | M6: =K6-L6 -> 256.06 | N6: =IF(K6<0,"FAIL","OK") -> OK
A7: 3 | B7: =B6+IF(L6>0,1,0) -> 1 | C7: =MIN(INDEX(Inputs!$E$26:$E$28,B7)+(A7-1)*Inputs!$B$17,Inputs!$B$23) -> 7 | D7: =C7*Inputs!$B$13 -> 49 | E7: =Inputs!$B$18*(1+Inputs!D$7*(Inputs!$B$19-1))*Inputs!D$5*Inputs!D$6 -> 8.58 | F7: =D7*Inputs!D$8 -> 49 | G7: =F7*E7 -> 420.42 | H7: =F7*Inputs!D$7 -> 29.4 | I7: =MAX(0,H7-IF(A7=1,Inputs!$B$21,0))*Inputs!$B$20 -> 88.2 | J7: =Inputs!$B$15+(A7-1)*Inputs!$B$16+SUMIF(Inputs!$A$26:$A$28,"<="&B7,Inputs!$D$26:$D$28) -> 190 | K7: =M6+G7-I7-J7 -> 398.28 | L7: =IF(B7>=COUNT(Inputs!$A$26:$A$28),0,IF(AND(K7>=0,A7>=INDEX(Inputs!$B$26:$B$28,B7+1),K7>=INDEX(Inputs!$C$26:$C$28,B7+1)+Inputs!$B$22),INDEX(Inputs!$C$26:$C$28,B7+1),0)) -> 150 | M7: =K7-L7 -> 248.28 | N7: =IF(K7<0,"FAIL","OK") -> OK
A8: 4 | B8: =B7+IF(L7>0,1,0) -> 2 | C8: =MIN(INDEX(Inputs!$E$26:$E$28,B8)+(A8-1)*Inputs!$B$17,Inputs!$B$23) -> 11 | D8: =C8*Inputs!$B$13 -> 77 | E8: =Inputs!$B$18*(1+Inputs!D$7*(Inputs!$B$19-1))*Inputs!D$5*Inputs!D$6 -> 8.58 | F8: =D8*Inputs!D$8 -> 77 | G8: =F8*E8 -> 660.66 | H8: =F8*Inputs!D$7 -> 46.2 | I8: =MAX(0,H8-IF(A8=1,Inputs!$B$21,0))*Inputs!$B$20 -> 138.6 | J8: =Inputs!$B$15+(A8-1)*Inputs!$B$16+SUMIF(Inputs!$A$26:$A$28,"<="&B8,Inputs!$D$26:$D$28) -> 280 | K8: =M7+G8-I8-J8 -> 490.34 | L8: =IF(B8>=COUNT(Inputs!$A$26:$A$28),0,IF(AND(K8>=0,A8>=INDEX(Inputs!$B$26:$B$28,B8+1),K8>=INDEX(Inputs!$C$26:$C$28,B8+1)+Inputs!$B$22),INDEX(Inputs!$C$26:$C$28,B8+1),0)) -> 0 | M8: =K8-L8 -> 490.34 | N8: =IF(K8<0,"FAIL","OK") -> OK
A9: 5 | B9: =B8+IF(L8>0,1,0) -> 2 | C9: =MIN(INDEX(Inputs!$E$26:$E$28,B9)+(A9-1)*Inputs!$B$17,Inputs!$B$23) -> 12 | D9: =C9*Inputs!$B$13 -> 84 | E9: =Inputs!$B$18*(1+Inputs!D$7*(Inputs!$B$19-1))*Inputs!D$5*Inputs!D$6 -> 8.58 | F9: =D9*Inputs!D$8 -> 84 | G9: =F9*E9 -> 720.72 | H9: =F9*Inputs!D$7 -> 50.4 | I9: =MAX(0,H9-IF(A9=1,Inputs!$B$21,0))*Inputs!$B$20 -> 151.2 | J9: =Inputs!$B$15+(A9-1)*Inputs!$B$16+SUMIF(Inputs!$A$26:$A$28,"<="&B9,Inputs!$D$26:$D$28) -> 310 | K9: =M8+G9-I9-J9 -> 749.86 | L9: =IF(B9>=COUNT(Inputs!$A$26:$A$28),0,IF(AND(K9>=0,A9>=INDEX(Inputs!$B$26:$B$28,B9+1),K9>=INDEX(Inputs!$C$26:$C$28,B9+1)+Inputs!$B$22),INDEX(Inputs!$C$26:$C$28,B9+1),0)) -> 0 | M9: =K9-L9 -> 749.86 | N9: =IF(K9<0,"FAIL","OK") -> OK
A10: 6 | B10: =B9+IF(L9>0,1,0) -> 2 | C10: =MIN(INDEX(Inputs!$E$26:$E$28,B10)+(A10-1)*Inputs!$B$17,Inputs!$B$23) -> 13 | D10: =C10*Inputs!$B$13 -> 91 | E10: =Inputs!$B$18*(1+Inputs!D$7*(Inputs!$B$19-1))*Inputs!D$5*Inputs!D$6 -> 8.58 | F10: =D10*Inputs!D$8 -> 91 | G10: =F10*E10 -> 780.78 | H10: =F10*Inputs!D$7 -> 54.6 | I10: =MAX(0,H10-IF(A10=1,Inputs!$B$21,0))*Inputs!$B$20 -> 163.8 | J10: =Inputs!$B$15+(A10-1)*Inputs!$B$16+SUMIF(Inputs!$A$26:$A$28,"<="&B10,Inputs!$D$26:$D$28) -> 340 | K10: =M9+G10-I10-J10 -> 1026.84 | L10: =IF(B10>=COUNT(Inputs!$A$26:$A$28),0,IF(AND(K10>=0,A10>=INDEX(Inputs!$B$26:$B$28,B10+1),K10>=INDEX(Inputs!$C$26:$C$28,B10+1)+Inputs!$B$22),INDEX(Inputs!$C$26:$C$28,B10+1),0)) -> 300 | M10: =K10-L10 -> 726.84 | N10: =IF(K10<0,"FAIL","OK") -> OK
A11: 7 | B11: =B10+IF(L10>0,1,0) -> 3 | C11: =MIN(INDEX(Inputs!$E$26:$E$28,B11)+(A11-1)*Inputs!$B$17,Inputs!$B$23) -> 14 | D11: =C11*Inputs!$B$13 -> 98 | E11: =Inputs!$B$18*(1+Inputs!D$7*(Inputs!$B$19-1))*Inputs!D$5*Inputs!D$6 -> 8.58 | F11: =D11*Inputs!D$8 -> 98 | G11: =F11*E11 -> 840.84 | H11: =F11*Inputs!D$7 -> 58.8 | I11: =MAX(0,H11-IF(A11=1,Inputs!$B$21,0))*Inputs!$B$20 -> 176.4 | J11: =Inputs!$B$15+(A11-1)*Inputs!$B$16+SUMIF(Inputs!$A$26:$A$28,"<="&B11,Inputs!$D$26:$D$28) -> 460 | K11: =M10+G11-I11-J11 -> 931.28 | L11: =IF(B11>=COUNT(Inputs!$A$26:$A$28),0,IF(AND(K11>=0,A11>=INDEX(Inputs!$B$26:$B$28,B11+1),K11>=INDEX(Inputs!$C$26:$C$28,B11+1)+Inputs!$B$22),INDEX(Inputs!$C$26:$C$28,B11+1),0)) -> 0 | M11: =K11-L11 -> 931.28 | N11: =IF(K11<0,"FAIL","OK") -> OK
A12: 8 | B12: =B11+IF(L11>0,1,0) -> 3 | C12: =MIN(INDEX(Inputs!$E$26:$E$28,B12)+(A12-1)*Inputs!$B$17,Inputs!$B$23) -> 14 | D12: =C12*Inputs!$B$13 -> 98 | E12: =Inputs!$B$18*(1+Inputs!D$7*(Inputs!$B$19-1))*Inputs!D$5*Inputs!D$6 -> 8.58 | F12: =D12*Inputs!D$8 -> 98 | G12: =F12*E12 -> 840.84 | H12: =F12*Inputs!D$7 -> 58.8 | I12: =MAX(0,H12-IF(A12=1,Inputs!$B$21,0))*Inputs!$B$20 -> 176.4 | J12: =Inputs!$B$15+(A12-1)*Inputs!$B$16+SUMIF(Inputs!$A$26:$A$28,"<="&B12,Inputs!$D$26:$D$28) -> 490 | K12: =M11+G12-I12-J12 -> 1105.72 | L12: =IF(B12>=COUNT(Inputs!$A$26:$A$28),0,IF(AND(K12>=0,A12>=INDEX(Inputs!$B$26:$B$28,B12+1),K12>=INDEX(Inputs!$C$26:$C$28,B12+1)+Inputs!$B$22),INDEX(Inputs!$C$26:$C$28,B12+1),0)) -> 0 | M12: =K12-L12 -> 1105.72 | N12: =IF(K12<0,"FAIL","OK") -> OK
A13: 9 | B13: =B12+IF(L12>0,1,0) -> 3 | C13: =MIN(INDEX(Inputs!$E$26:$E$28,B13)+(A13-1)*Inputs!$B$17,Inputs!$B$23) -> 14 | D13: =C13*Inputs!$B$13 -> 98 | E13: =Inputs!$B$18*(1+Inputs!D$7*(Inputs!$B$19-1))*Inputs!D$5*Inputs!D$6 -> 8.58 | F13: =D13*Inputs!D$8 -> 98 | G13: =F13*E13 -> 840.84 | H13: =F13*Inputs!D$7 -> 58.8 | I13: =MAX(0,H13-IF(A13=1,Inputs!$B$21,0))*Inputs!$B$20 -> 176.4 | J13: =Inputs!$B$15+(A13-1)*Inputs!$B$16+SUMIF(Inputs!$A$26:$A$28,"<="&B13,Inputs!$D$26:$D$28) -> 520 | K13: =M12+G13-I13-J13 -> 1250.16 | L13: =IF(B13>=COUNT(Inputs!$A$26:$A$28),0,IF(AND(K13>=0,A13>=INDEX(Inputs!$B$26:$B$28,B13+1),K13>=INDEX(Inputs!$C$26:$C$28,B13+1)+Inputs!$B$22),INDEX(Inputs!$C$26:$C$28,B13+1),0)) -> 0 | M13: =K13-L13 -> 1250.16 | N13: =IF(K13<0,"FAIL","OK") -> OK
A14: 10 | B14: =B13+IF(L13>0,1,0) -> 3 | C14: =MIN(INDEX(Inputs!$E$26:$E$28,B14)+(A14-1)*Inputs!$B$17,Inputs!$B$23) -> 14 | D14: =C14*Inputs!$B$13 -> 98 | E14: =Inputs!$B$18*(1+Inputs!D$7*(Inputs!$B$19-1))*Inputs!D$5*Inputs!D$6 -> 8.58 | F14: =D14*Inputs!D$8 -> 98 | G14: =F14*E14 -> 840.84 | H14: =F14*Inputs!D$7 -> 58.8 | I14: =MAX(0,H14-IF(A14=1,Inputs!$B$21,0))*Inputs!$B$20 -> 176.4 | J14: =Inputs!$B$15+(A14-1)*Inputs!$B$16+SUMIF(Inputs!$A$26:$A$28,"<="&B14,Inputs!$D$26:$D$28) -> 550 | K14: =M13+G14-I14-J14 -> 1364.6 | L14: =IF(B14>=COUNT(Inputs!$A$26:$A$28),0,IF(AND(K14>=0,A14>=INDEX(Inputs!$B$26:$B$28,B14+1),K14>=INDEX(Inputs!$C$26:$C$28,B14+1)+Inputs!$B$22),INDEX(Inputs!$C$26:$C$28,B14+1),0)) -> 0 | M14: =K14-L14 -> 1364.6 | N14: =IF(K14<0,"FAIL","OK") -> OK
A15: 11 | B15: =B14+IF(L14>0,1,0) -> 3 | C15: =MIN(INDEX(Inputs!$E$26:$E$28,B15)+(A15-1)*Inputs!$B$17,Inputs!$B$23) -> 14 | D15: =C15*Inputs!$B$13 -> 98 | E15: =Inputs!$B$18*(1+Inputs!D$7*(Inputs!$B$19-1))*Inputs!D$5*Inputs!D$6 -> 8.58 | F15: =D15*Inputs!D$8 -> 98 | G15: =F15*E15 -> 840.84 | H15: =F15*Inputs!D$7 -> 58.8 | I15: =MAX(0,H15-IF(A15=1,Inputs!$B$21,0))*Inputs!$B$20 -> 176.4 | J15: =Inputs!$B$15+(A15-1)*Inputs!$B$16+SUMIF(Inputs!$A$26:$A$28,"<="&B15,Inputs!$D$26:$D$28) -> 580 | K15: =M14+G15-I15-J15 -> 1449.04 | L15: =IF(B15>=COUNT(Inputs!$A$26:$A$28),0,IF(AND(K15>=0,A15>=INDEX(Inputs!$B$26:$B$28,B15+1),K15>=INDEX(Inputs!$C$26:$C$28,B15+1)+Inputs!$B$22),INDEX(Inputs!$C$26:$C$28,B15+1),0)) -> 0 | M15: =K15-L15 -> 1449.04 | N15: =IF(K15<0,"FAIL","OK") -> OK
A16: 12 | B16: =B15+IF(L15>0,1,0) -> 3 | C16: =MIN(INDEX(Inputs!$E$26:$E$28,B16)+(A16-1)*Inputs!$B$17,Inputs!$B$23) -> 14 | D16: =C16*Inputs!$B$13 -> 98 | E16: =Inputs!$B$18*(1+Inputs!D$7*(Inputs!$B$19-1))*Inputs!D$5*Inputs!D$6 -> 8.58 | F16: =D16*Inputs!D$8 -> 98 | G16: =F16*E16 -> 840.84 | H16: =F16*Inputs!D$7 -> 58.8 | I16: =MAX(0,H16-IF(A16=1,Inputs!$B$21,0))*Inputs!$B$20 -> 176.4 | J16: =Inputs!$B$15+(A16-1)*Inputs!$B$16+SUMIF(Inputs!$A$26:$A$28,"<="&B16,Inputs!$D$26:$D$28) -> 610 | K16: =M15+G16-I16-J16 -> 1503.48 | L16: =IF(B16>=COUNT(Inputs!$A$26:$A$28),0,IF(AND(K16>=0,A16>=INDEX(Inputs!$B$26:$B$28,B16+1),K16>=INDEX(Inputs!$C$26:$C$28,B16+1)+Inputs!$B$22),INDEX(Inputs!$C$26:$C$28,B16+1),0)) -> 0 | M16: =K16-L16 -> 1503.48 | N16: =IF(K16<0,"FAIL","OK") -> OK
A17: 13 | B17: =B16+IF(L16>0,1,0) -> 3 | C17: =MIN(INDEX(Inputs!$E$26:$E$28,B17)+(A17-1)*Inputs!$B$17,Inputs!$B$23) -> 14 | D17: =C17*Inputs!$B$13 -> 98 | E17: =Inputs!$B$18*(1+Inputs!D$7*(Inputs!$B$19-1))*Inputs!D$5*Inputs!D$6 -> 8.58 | F17: =D17*Inputs!D$8 -> 98 | G17: =F17*E17 -> 840.84 | H17: =F17*Inputs!D$7 -> 58.8 | I17: =MAX(0,H17-IF(A17=1,Inputs!$B$21,0))*Inputs!$B$20 -> 176.4 | J17: =Inputs!$B$15+(A17-1)*Inputs!$B$16+SUMIF(Inputs!$A$26:$A$28,"<="&B17,Inputs!$D$26:$D$28) -> 640 | K17: =M16+G17-I17-J17 -> 1527.92 | L17: =IF(B17>=COUNT(Inputs!$A$26:$A$28),0,IF(AND(K17>=0,A17>=INDEX(Inputs!$B$26:$B$28,B17+1),K17>=INDEX(Inputs!$C$26:$C$28,B17+1)+Inputs!$B$22),INDEX(Inputs!$C$26:$C$28,B17+1),0)) -> 0 | M17: =K17-L17 -> 1527.92 | N17: =IF(K17<0,"FAIL","OK") -> OK
... A30: 26 | B30: =B29+IF(L29>0,1,0) -> 3 | C30: =MIN(INDEX(Inputs!$E$26:$E$28,B30)+(A30-1)*Inputs!$B$17,Inputs!$B$23) -> 14 | D30: =C30*Inputs!$B$13 -> 98 | E30: =Inputs!$B$18*(1+Inputs!D$7*(Inputs!$B$19-1))*Inputs!D$5*Inputs!D$6 -> 8.58 | F30: =D30*Inputs!D$8 -> 98 | G30: =F30*E30 -> 840.84 | H30: =F30*Inputs!D$7 -> 58.8 | I30: =MAX(0,H30-IF(A30=1,Inputs!$B$21,0))*Inputs!$B$20 -> 176.4 | J30: =Inputs!$B$15+(A30-1)*Inputs!$B$16+SUMIF(Inputs!$A$26:$A$28,"<="&B30,Inputs!$D$26:$D$28) -> 1030 | K30: =M29+G30-I30-J30 -> -884.36 | L30: =IF(B30>=COUNT(Inputs!$A$26:$A$28),0,IF(AND(K30>=0,A30>=INDEX(Inputs!$B$26:$B$28,B30+1),K30>=INDEX(Inputs!$C$26:$C$28,B30+1)+Inputs!$B$22),INDEX(Inputs!$C$26:$C$28,B30+1),0)) -> 0 | M30: =K30-L30 -> -884.36 | N30: =IF(K30<0,"FAIL","OK") -> FAIL
